snek_inspyred/__init__.py
snek_inspyred/conf/__init__.py
snek_inspyred/conf/appearence.conf
snek_inspyred/conf/audio_conf.py
snek_inspyred/conf/errors.py
snek_inspyred/game/__init__.py
snek_inspyred/game/audio/__init__.py
snek_inspyred/game/audio/assets/__init__.py
snek_inspyred/game/audio/assets/eat_food_1.mp3
snek_inspyred/game/audio/assets/eat_food_1.wav
snek_inspyred/game/audio/assets/start_fanfare_1.wav
snek_inspyred/game/audio/assets/start_fanfare_2.wav
snek_inspyred/game/audio/conf/__init__.py
snek_inspyred/game/audio/conf/conf_files/audio.ini
snek_inspyred/game/audio/conf/conf_files/sound_set.ini
snek_inspyred/game/audio/conf/conf_files/sounds.lib
snek_inspyred/game/field/__init__.py
snek_inspyred/game/models/__init__.py
snek_inspyred/helpers/__init__.py
snek_inspyred/main.py
snek_inspyred-1.1.dist-info/entry_points.txt
snek_inspyred-1.1.dist-info/WHEEL
snek_inspyred-1.1.dist-info/METADATA
snek_inspyred-1.1.dist-info/RECORD
